aimagelab/__init__.py
aimagelab/olj/__init__.py
aimagelab/olj/base.py
aimagelab/olj/evaluators/__init__.py
aimagelab/olj/evaluators/base.py
aimagelab/olj/evaluators/lab00.py
pyOLJ-0.0.dev32.dist-info/METADATA
pyOLJ-0.0.dev32.dist-info/WHEEL
pyOLJ-0.0.dev32.dist-info/top_level.txt
pyOLJ-0.0.dev32.dist-info/RECORD
