Metadata-Version: 2.1
Name: pyOLJ
Version: 0.0.dev32
Summary: AImageLab Code Judge for Python
Home-page: https://github.com/aimagelab/pyOLJ
Author: Lorenzo Baraldi
Author-email: lorenzo.baraldi@unimore.it
License: UNKNOWN
Platform: UNKNOWN
Classifier: Programming Language :: Python :: 3
Classifier: License :: OSI Approved :: BSD License
Classifier: Operating System :: OS Independent
Requires-Dist: numpy
Requires-Dist: torch
